src/__init__.py
src/test.py
lik-0.0.1.dist-info/LICENSE
lik-0.0.1.dist-info/METADATA
lik-0.0.1.dist-info/WHEEL
lik-0.0.1.dist-info/top_level.txt
lik-0.0.1.dist-info/RECORD
