Metadata-Version: 2.1
Name: lik
Version: 0.0.1
Summary: test my lik package
Home-page: https://github.com/psychAo/lik
Author: psychAo
Author-email: psychao@outlook.com
License-File: LICENSE
Requires-Dist: numpy
